[
  {
    "keyword": "Feature",
    "name": "Products",
    "line": 1,
    "id": "products",
    "tags": [],
    "uri": "products.feature",
    "elements": [
      {
        "id": "products;[tcp-pro-003]-user-sorts-list-of-product",
        "keyword": "Scenario",
        "line": 16,
        "name": "[TCP-PRO-003] User sorts list of product",
        "tags": [
          {
            "name": "@positive",
            "line": 15
          }
        ],
        "type": "scenario",
        "steps": [
          {
            "arguments": [],
            "keyword": "Given ",
            "line": 3,
            "name": "User has login as 'standard_user'",
            "result": {
              "status": "passed",
              "duration": 2881000000
            }
          },
          {
            "arguments": [],
            "keyword": "When ",
            "line": 17,
            "name": "User selects Price low to high on option of sorting icon",
            "result": {
              "status": "passed",
              "duration": 142000000
            }
          },
          {
            "arguments": [],
            "keyword": "Then ",
            "line": 18,
            "name": "User should sees product has sorted by Price low to high",
            "result": {
              "status": "passed",
              "duration": 12000000
            }
          }
        ]
      }
    ]
  }
]